Compiled from "OverrideDemo.java"
public class com.zwx.jvm.override.OverrideDemo {
  public com.zwx.jvm.override.OverrideDemo();
    Code:
       0: aload_0
       1: invokespecial #1                  // Method java/lang/Object."<init>":()V
       4: return

  public static void main(java.lang.String[]);
    Code:
       0: new           #2                  // class com/zwx/jvm/override/OverrideDemo$Man
       3: dup
       4: invokespecial #3                  // Method com/zwx/jvm/override/OverrideDemo$Man."<init>":()V
       7: astore_1
       8: new           #4                  // class com/zwx/jvm/override/OverrideDemo$WoMan
      11: dup
      12: invokespecial #5                  // Method com/zwx/jvm/override/OverrideDemo$WoMan."<init>":()V
      15: astore_2
      16: aload_1
      17: aload_1
      18: invokevirtual #6                  // Method com/zwx/jvm/override/OverrideDemo$Human.hello:(Lcom/zwx/jvm/override/OverrideDemo$Human;)V
      21: aload_1
      22: aload_2
      23: invokevirtual #6                  // Method com/zwx/jvm/override/OverrideDemo$Human.hello:(Lcom/zwx/jvm/override/OverrideDemo$Human;)V
      26: aload_2
      27: aload_2
      28: invokevirtual #6                  // Method com/zwx/jvm/override/OverrideDemo$Human.hello:(Lcom/zwx/jvm/override/OverrideDemo$Human;)V
      31: aload_2
      32: aload_1
      33: invokevirtual #6                  // Method com/zwx/jvm/override/OverrideDemo$Human.hello:(Lcom/zwx/jvm/override/OverrideDemo$Human;)V
      36: return
}
